fuzzyfiles/LICENSE
fuzzyfiles/README.md
fuzzyfiles/__init__.py
fuzzyfiles/requirements.txt
fuzzyfiles/thirdparty.json
fuzzyfiles-0.11.dist-info/LICENSE.rst
fuzzyfiles-0.11.dist-info/METADATA
fuzzyfiles-0.11.dist-info/WHEEL
fuzzyfiles-0.11.dist-info/top_level.txt
fuzzyfiles-0.11.dist-info/RECORD
