Metadata-Version: 2.1
Name: fuzzyfiles
Version: 0.11
Summary: Binary fuzzy matching in all file types [fzf (pre-filter)/rapidfuzz (finds the best result)]
Home-page: https://github.com/hansalemaos/fuzzyfiles
Author: Johannes Fischer
Author-email: aulasparticularesdealemaosp@gmail.com
License: MIT
Keywords: fuzzy,matching,fuzzywuzzy,rapidfuzz,fzf
Classifier: Development Status :: 4 - Beta
Classifier: Programming Language :: Python :: 3 :: Only
Classifier: Programming Language :: Python :: 3.10
Classifier: Topic :: Software Development :: Libraries :: Python Modules
Classifier: Topic :: Utilities
License-File: LICENSE.rst
Requires-Dist: flatten-everything
Requires-Dist: multisubprocess
Requires-Dist: numpy
Requires-Dist: pandas
Requires-Dist: rapidfuzz
